.gitignore
README.txt
license.txt
mnistExample.py
setup.py
gdbn/__init__.py
gdbn/activationFunctions.py
gdbn/counter.py
gdbn/dbn.py
gdbn/pretrain.py
gdbn.egg-info/PKG-INFO
gdbn.egg-info/SOURCES.txt
gdbn.egg-info/dependency_links.txt
gdbn.egg-info/requires.txt
gdbn.egg-info/top_level.txt
local/README.txt
local/license.txt
local/mnistExample.py