Metadata-Version: 1.0
Name: gdbn
Version: 0.1
Summary: Pre-trained deep neural networks
Home-page: http://www.cs.toronto.edu/~gdahl/
Author: George Dahl
Author-email: UNKNOWN
License: MIT (see license.txt)
Platform: UNKNOWN
